{
  "num_3": [
    582,
    592
  ],
  "num_6": [
    638,
    592
  ],
  "num_9": [
    694,
    592
  ],
  "num_12": [
    750,
    592
  ],
  "num_15": [
    805,
    592
  ],
  "num_18": [
    861,
    592
  ],
  "num_21": [
    917,
    592
  ],
  "num_24": [
    973,
    592
  ],
  "num_27": [
    1029,
    592
  ],
  "num_30": [
    1085,
    592
  ],
  "num_33": [
    1141,
    592
  ],
  "num_36": [
    1197,
    592
  ],
  "num_2": [
    582,
    631
  ],
  "num_5": [
    638,
    631
  ],
  "num_8": [
    694,
    631
  ],
  "num_11": [
    750,
    631
  ],
  "num_14": [
    805,
    631
  ],
  "num_17": [
    861,
    631
  ],
  "num_20": [
    917,
    631
  ],
  "num_23": [
    973,
    631
  ],
  "num_26": [
    1029,
    631
  ],
  "num_29": [
    1085,
    631
  ],
  "num_32": [
    1141,
    631
  ],
  "num_35": [
    1197,
    631
  ],
  "num_1": [
    582,
    671
  ],
  "num_4": [
    638,
    671
  ],
  "num_7": [
    694,
    671
  ],
  "num_10": [
    750,
    671
  ],
  "num_13": [
    805,
    671
  ],
  "num_16": [
    861,
    671
  ],
  "num_19": [
    917,
    671
  ],
  "num_22": [
    973,
    671
  ],
  "num_25": [
    1029,
    671
  ],
  "num_28": [
    1085,
    671
  ],
  "num_31": [
    1141,
    671
  ],
  "num_34": [
    1197,
    671
  ],
  "num_0": [
    528,
    632
  ],
  "col3_btn": [
    1247,
    593
  ],
  "col2_btn": [
    1247,
    632
  ],
  "col1_btn": [
    1247,
    671
  ],
  "1st12": [
    666,
    709
  ],
  "2nd12": [
    890,
    709
  ],
  "3rd12": [
    1113,
    709
  ],
  "1-18": [
    610,
    744
  ],
  "even": [
    722,
    744
  ],
  "red": [
    834,
    744
  ],
  "black": [
    946,
    744
  ],
  "odd": [
    1058,
    744
  ],
  "19-36": [
    1170,
    744
  ],
  "ds1": [
    610,
    632
  ],
  "ds7": [
    722,
    632
  ],
  "ds13": [
    833,
    632
  ],
  "ds19": [
    945,
    632
  ],
  "ds25": [
    1057,
    632
  ],
  "ds31": [
    1169,
    632
  ],
  "_status_region": {
    "x": 880,
    "y": 518,
    "w": 308,
    "h": 27
  },
  "_last_number_region": {
    "x": 1315,
    "y": 263,
    "w": 67,
    "h": 41
  },
  "_balance_region": {
    "x": 465,
    "y": 826,
    "w": 120,
    "h": 38
  },
  "_meta": {
    "image_w": 1920,
    "image_h": 1080,
    "cell_w": 56,
    "cell_h": 39
  },
  "cr_2_3_5_6": [
    610,
    612
  ],
  "cr_1_2_4_5": [
    610,
    651
  ],
  "cr_5_6_8_9": [
    666,
    612
  ],
  "cr_4_5_7_8": [
    666,
    651
  ],
  "cr_8_9_11_12": [
    722,
    612
  ],
  "cr_7_8_10_11": [
    722,
    651
  ],
  "cr_11_12_14_15": [
    778,
    612
  ],
  "cr_10_11_13_14": [
    778,
    651
  ],
  "cr_14_15_17_18": [
    833,
    612
  ],
  "cr_13_14_16_17": [
    833,
    651
  ],
  "cr_17_18_20_21": [
    889,
    612
  ],
  "cr_16_17_19_20": [
    889,
    651
  ],
  "cr_20_21_23_24": [
    945,
    612
  ],
  "cr_19_20_22_23": [
    945,
    651
  ],
  "cr_23_24_26_27": [
    1001,
    612
  ],
  "cr_22_23_25_26": [
    1001,
    651
  ],
  "cr_26_27_29_30": [
    1057,
    612
  ],
  "cr_25_26_28_29": [
    1057,
    651
  ],
  "cr_29_30_32_33": [
    1113,
    612
  ],
  "cr_28_29_31_32": [
    1113,
    651
  ],
  "cr_32_33_35_36": [
    1169,
    612
  ],
  "cr_31_32_34_35": [
    1169,
    651
  ],
  "btn_undo": [
    924,
    822
  ],
  "chip_0.10": [
    965,
    822
  ],
  "chip_0.50": [
    1006,
    822
  ],
  "chip_1": [
    1048,
    822
  ],
  "chip_5": [
    1090,
    822
  ],
  "chip_25": [
    1131,
    822
  ],
  "chip_100": [
    1173,
    822
  ],
  "_total_bet_region": {
    "x": 638,
    "y": 826,
    "w": 122,
    "h": 38
  },
  "chip_500": [
    1214,
    822
  ],
  "btn_repeat": [
    1255,
    822
  ]
}